SharedMemory/SMError.py
SharedMemory/SharedMemory.py
SharedMemory/__init__.py
SharedMemory-1.6.0.dist-info/LICENSE
SharedMemory-1.6.0.dist-info/METADATA
SharedMemory-1.6.0.dist-info/WHEEL
SharedMemory-1.6.0.dist-info/top_level.txt
SharedMemory-1.6.0.dist-info/RECORD
