Metadata-Version: 2.1
Name: SharedMemory
Version: 1.6.0
Summary: SharedMemory
Home-page: https://github.com/Zentetsu/SharedMemory
Author: Zentetsu
License: GPLv3
Requires-Python: >=3.8
License-File: LICENSE
Requires-Dist: posix-ipc
Requires-Dist: numpy
